pyconverters_inscriptis/__init__.py
pyconverters_inscriptis/inscriptis.py
pyconverters_inscriptis-0.5.198.dist-info/entry_points.txt
pyconverters_inscriptis-0.5.198.dist-info/WHEEL
pyconverters_inscriptis-0.5.198.dist-info/METADATA
pyconverters_inscriptis-0.5.198.dist-info/RECORD
